odoo/addons/account_invoice_transmit_method_substitution_rule/README.rst
odoo/addons/account_invoice_transmit_method_substitution_rule/__init__.py
odoo/addons/account_invoice_transmit_method_substitution_rule/__manifest__.py
odoo/addons/account_invoice_transmit_method_substitution_rule/demo/transmit_method_substitution_rule.xml
odoo/addons/account_invoice_transmit_method_substitution_rule/i18n/account_invoice_transmit_method_substitution_rule.pot
odoo/addons/account_invoice_transmit_method_substitution_rule/i18n/de.po
odoo/addons/account_invoice_transmit_method_substitution_rule/i18n/es.po
odoo/addons/account_invoice_transmit_method_substitution_rule/i18n/it.po
odoo/addons/account_invoice_transmit_method_substitution_rule/models/__init__.py
odoo/addons/account_invoice_transmit_method_substitution_rule/models/account_invoice.py
odoo/addons/account_invoice_transmit_method_substitution_rule/models/transmit_method_substitution_rule.py
odoo/addons/account_invoice_transmit_method_substitution_rule/readme/CONTRIBUTORS.md
odoo/addons/account_invoice_transmit_method_substitution_rule/readme/DESCRIPTION.md
odoo/addons/account_invoice_transmit_method_substitution_rule/readme/USAGE.md
odoo/addons/account_invoice_transmit_method_substitution_rule/security/transmit_method_substitution_rule.xml
odoo/addons/account_invoice_transmit_method_substitution_rule/static/description/icon.png
odoo/addons/account_invoice_transmit_method_substitution_rule/static/description/index.html
odoo/addons/account_invoice_transmit_method_substitution_rule/tests/__init__.py
odoo/addons/account_invoice_transmit_method_substitution_rule/tests/test_account_invoice_transmit_method_substitution_rule.py
odoo/addons/account_invoice_transmit_method_substitution_rule/views/transmit_method_substitution_rule.xml
odoo_addon_account_invoice_transmit_method_substitution_rule-18.0.1.0.0.5.dist-info/METADATA
odoo_addon_account_invoice_transmit_method_substitution_rule-18.0.1.0.0.5.dist-info/WHEEL
odoo_addon_account_invoice_transmit_method_substitution_rule-18.0.1.0.0.5.dist-info/top_level.txt
odoo_addon_account_invoice_transmit_method_substitution_rule-18.0.1.0.0.5.dist-info/RECORD
